[{"Controls":[{"Control":{"Field":"Value","Error":"","Initial":null,"Latch":false,"Transform":"","Address":"/oscControl/button1","Argument":0,"Debug":10},"Controls":null,"Disabled":false,"Type":"OscControl"}],"Disabled":false,"Effect":{"Effects":[{"Controls":null,"Disabled":false,"Effect":{"Color":[255,255,255],"Speed":0.1,"Position":46,"Width":10,"Bounce":true},"Type":"Scanner"}],"Value":0},"Type":"Trigger"},{"Controls":[{"Control":{"Field":"Offset","Error":"","Initial":null,"Latch":false,"Transform":"v*100","Address":"/oscControl/slider3","Argument":0,"Debug":0.4990961},"Controls":null,"Disabled":false,"Type":"OscControl"}],"Disabled":false,"Effect":{"N":116,"Offset":49,"Reverse":false,"Blend":{"Offset":0,"Reverse":false,"Force":false,"Factor":0.5,"Func":"lab"}},"Type":"Whoosh"},{"Controls":[{"Control":{"Field":"Level","Error":"","Initial":null,"Latch":false,"Transform":"v*255","Address":"/oscControl/slider4","Argument":0,"Debug":0.9816817},"Controls":null,"Disabled":false,"Type":"OscControl"}],"Disabled":false,"Effect":{"Level":250,"Func":"hsl"},"Type":"Brightness"},{"Controls":null,"Disabled":false,"Effect":{"Effects":[{"Controls":[{"Control":{"Field":"Size","Error":"","Initial":null,"Latch":false,"Transform":"","Address":"/oscControl/button1","Argument":0,"Debug":10},"Controls":null,"Disabled":false,"Type":"OscControl"},{"Control":{"Field":"Size","Error":"","Initial":null,"Latch":false,"Transform":"","Address":"","Argument":0,"Debug":null},"Controls":null,"Disabled":false,"Type":"OscControl"}],"Disabled":false,"Effect":{"Size":5,"Depth":5,"Speed":0.37,"Blend":{"Offset":0,"Reverse":false,"Force":false,"Factor":0.5,"Func":"lab"},"Reverse":true,"NewMethod":true},"Type":"Rainbow"}],"Size":10,"BlendA":{"Offset":0,"Reverse":true,"Force":false,"Factor":0.5,"Func":"lab"},"BlendB":{"Offset":5,"Reverse":false,"Force":false,"Factor":0.5,"Func":"lab"}},"Type":"Mirror"},{"Controls":null,"Disabled":false,"Effect":{"Type":"grid","Blend":{"Offset":0,"Reverse":false,"Force":false,"Factor":0.5,"Func":"lab"},"Effects":[{"Controls":[{"Control":{"Field":"Position","Error":"","Initial":null,"Latch":true,"Transform":"(c+1)%100","Value":"1"},"Controls":null,"Disabled":false,"Type":"FixedValueControl"}],"Disabled":false,"Effect":{"Color":[0,0,0],"Speed":0,"Position":98,"Width":2,"Bounce":true},"Type":"Scanner"}]},"Type":"Layout"},{"Controls":[{"Control":{"Field":"Value","Error":"","Initial":null,"Latch":false,"Transform":"v*255","Address":"/oscControl/slider2","Argument":0,"Debug":0.5056746},"Controls":null,"Disabled":false,"Type":"OscControl"}],"Disabled":false,"Effect":{"Value":128},"Type":"Gamma"},{"Controls":null,"Disabled":false,"Effect":{"Name":"reduce-green.js","Args":null},"Type":"Script"}]