[{"Controls":null,"Disabled":true,"Effect":{},"Type":"Clear"},{"Controls":[{"Control":{"Field":"N","Error":"","Initial":null,"Latch":false,"Transform":"","Address":"/N","Argument":0,"Debug":15},"Controls":null,"Disabled":false,"Type":"OscControl"}],"Disabled":false,"Effect":{"Width":16,"Height":16,"Color":[51,9,140],"StartingCells":175,"NumPrevStates":0,"Restart":true,"N":15},"Type":"GameOfLife"},{"Controls":[{"Control":{"Field":"Blend.Factor","Error":"","Initial":null,"Latch":false,"Transform":"+v","Value":"0.55"},"Controls":null,"Disabled":true,"Type":"FixedValueControl"},{"Control":{"Field":"Blend.Factor","Error":"","Initial":"0.05","Latch":true,"Transform":"+v","Address":"/blend","Argument":0,"Debug":0.003},"Controls":null,"Disabled":false,"Type":"OscControl"},{"Control":{"Field":"Size","Error":"","Initial":null,"Latch":false,"Transform":"+v","Value":"5000"},"Controls":null,"Disabled":false,"Type":"FixedValueControl"},{"Control":{"Field":"Speed","Error":"","Initial":null,"Latch":false,"Transform":"+v*4","Address":"/vslider1","Argument":0,"Debug":null},"Controls":null,"Disabled":false,"Type":"OscControl"}],"Disabled":false,"Effect":{"Size":5000,"Depth":5,"Speed":0.14,"Blend":{"Offset":0,"Reverse":false,"Force":false,"Factor":0.003000000026077032,"Func":"rgb"},"Reverse":false,"NewMethod":true},"Type":"Rainbow"},{"Controls":null,"Disabled":false,"Effect":{"Effects":[{"Controls":[{"Control":{"Field":"Value","Error":"","Initial":null,"Latch":false,"Transform":"","Function":"sin","Min":88,"Max":164,"Speed":5},"Controls":null,"Disabled":false,"Type":"TweenControl"}],"Disabled":false,"Effect":{"Value":101},"Type":"Gamma"}],"Enabled":false},"Type":"Toggle"},{"Controls":null,"Disabled":true,"Effect":{"N":7,"Offset":0,"Reverse":false,"Blend":{"Offset":0,"Reverse":false,"Force":false,"Factor":0.5,"Func":"rgb"}},"Type":"Whoosh"},{"Controls":[{"Control":{"Field":"Blend.Factor","Error":"","Initial":null,"Latch":false,"Transform":"+v","Value":"0.2"},"Controls":null,"Disabled":false,"Type":"FixedValueControl"}],"Disabled":true,"Effect":{"Blend":{"Offset":0,"Reverse":false,"Force":false,"Factor":0.2,"Func":"rgb"},"Effects":[{"Controls":null,"Disabled":false,"Effect":{"Effects":[{"Controls":null,"Disabled":false,"Effect":{"Name":"microphone.py","Args":null},"Type":"Script"}],"Size":1444,"BlendA":{"Offset":0,"Reverse":true,"Force":false,"Factor":0.5,"Func":"rgb"},"BlendB":{"Offset":722,"Reverse":false,"Force":false,"Factor":0.5,"Func":"rgb"}},"Type":"Mirror"},{"Controls":null,"Disabled":false,"Effect":{"N":50,"Offset":0,"Reverse":false,"Blend":{"Offset":0,"Reverse":false,"Force":false,"Factor":0.5,"Func":"rgb"}},"Type":"Whoosh"}],"Size":1444,"Offset":0},"Type":"Layer"},{"Controls":null,"Disabled":true,"Effect":{"Factor":24},"Type":"Sepia"}]